.gitignore
EXTERNAL_LICENSES.md
LICENSE.txt
MANIFEST.in
README.md
setup.cfg
setup.py
example/create_image_pdf
llpdf/EncodeDecode.py
llpdf/Exceptions.py
llpdf/FileRepr.py
llpdf/Logging.py
llpdf/Measurements.py
llpdf/PDFDocument.py
llpdf/PDFReader.py
llpdf/PDFTemplate.py
llpdf/PDFWriter.py
llpdf/__init__.py
llpdf.egg-info/PKG-INFO
llpdf.egg-info/SOURCES.txt
llpdf.egg-info/dependency_links.txt
llpdf.egg-info/top_level.txt
llpdf/filters/AddCropBoxFilter.py
llpdf/filters/AnalyzeFilter.py
llpdf/filters/DecompressFilter.py
llpdf/filters/DeleteOrphanedObjectsFilter.py
llpdf/filters/DownscaleImageOptimization.py
llpdf/filters/EmbedPayloadFilter.py
llpdf/filters/ExplicitLengthFilter.py
llpdf/filters/FlattenImageOptimization.py
llpdf/filters/PDFAFilter.py
llpdf/filters/PDFFilter.py
llpdf/filters/Relinker.py
llpdf/filters/RemoveDuplicateImageOptimization.py
llpdf/filters/RemoveMetadataFilter.py
llpdf/filters/SignFilter.py
llpdf/filters/TagFilter.py
llpdf/filters/__init__.py
llpdf/font/PostScriptEnums.py
llpdf/font/T1Canvas.py
llpdf/font/T1Command.py
llpdf/font/T1Font.py
llpdf/font/T1Glyph.py
llpdf/font/T1Interpreter.py
llpdf/font/T1PRNG.py
llpdf/font/TextWrapper.py
llpdf/font/__init__.py
llpdf/highlvl/PDFFunctions.py
llpdf/highlvl/PDFImageFunctions.py
llpdf/highlvl/__init__.py
llpdf/img/ImageReformatter.py
llpdf/img/NamedVector.py
llpdf/img/PDFExtImage.py
llpdf/img/PDFImage.py
llpdf/img/PnmPicture.py
llpdf/img/__init__.py
llpdf/interpreter/GraphicsInterpreter.py
llpdf/interpreter/__init__.py
llpdf/repr/GraphicsParser.py
llpdf/repr/PDFParser.py
llpdf/repr/PDFSerializer.py
llpdf/repr/ParseTools.py
llpdf/repr/__init__.py
llpdf/repr/tpg.py
llpdf/resources/__init__.py
llpdf/resources/bchr8a.pfb
llpdf/resources/sRGB_IEC61966-2-1_black_scaled.icc
llpdf/resources/seal.pdft
llpdf/resources/sign_form.pdft
llpdf/resources/xmp_metadata.xml
llpdf/tests/EncodeDecodeTest.py
llpdf/tests/GraphicsParserTest.py
llpdf/tests/OpenSSLVersionTests.py
llpdf/tests/PDFParserTest.py
llpdf/tests/__init__.py
llpdf/tests/__main__.py
llpdf/tools/OpenSSLVersion.py
llpdf/tools/X509Certificate.py
llpdf/tools/__init__.py
